{
  "version": "7",
  "dialect": "sqlite",
  "entries": [
    {
      "idx": 0,
      "version": "6",
      "when": 1751992054858,
      "tag": "0000_harsh_shatterstar",
      "breakpoints": true
    },
    {
      "idx": 1,
      "version": "6",
      "when": 1751992127828,
      "tag": "0001_clumsy_jack_murdock",
      "breakpoints": true
    },
    {
      "idx": 2,
      "version": "6",
      "when": 1751993292366,
      "tag": "0002_wooden_ben_grimm",
      "breakpoints": true
    },
    {
      "idx": 3,
      "version": "6",
      "when": 1752066129270,
      "tag": "0003_dazzling_stephen_strange",
      "breakpoints": true
    },
    {
      "idx": 4,
      "version": "6",
      "when": 1752305294525,
      "tag": "0004_thin_yellow_claw",
      "breakpoints": true
    },
    {
      "idx": 5,
      "version": "6",
      "when": 1752593286668,
      "tag": "0005_fancy_moira_mactaggert",
      "breakpoints": true
    },
    {
      "idx": 6,
      "version": "6",
      "when": 1752593367129,
      "tag": "0006_aromatic_zaran",
      "breakpoints": true
    }
  ]
}